gitconfig_cli/__init__.py
gitconfig_cli/cli.py
gitconfig_cli/git.py
gitconfig_cli/ssh.py
gitconfig_cli/utils.py
gitconfig_cli-1.0.0.dist-info/licenses/LICENSE
gitconfig_cli-1.0.0.dist-info/METADATA
gitconfig_cli-1.0.0.dist-info/WHEEL
gitconfig_cli-1.0.0.dist-info/entry_points.txt
gitconfig_cli-1.0.0.dist-info/top_level.txt
gitconfig_cli-1.0.0.dist-info/RECORD
