Metadata-Version: 2.4
Name: gitconfig-cli
Version: 1.0.0
Summary: Cross-platform Git + SSH configuration CLI
Author: Abdullah Shaikh
License:                     GNU GENERAL PUBLIC LICENSE
Requires-Python: >=3.10
License-File: LICENSE
Dynamic: license-file
